mystem/__init__.py
mystem/capslock.py
mystem/install.py
mystem/bin/.gitignore
python_mystem-0.0.2.dist-info/DESCRIPTION.rst
python_mystem-0.0.2.dist-info/LICENSE.txt
python_mystem-0.0.2.dist-info/METADATA
python_mystem-0.0.2.dist-info/RECORD
python_mystem-0.0.2.dist-info/WHEEL
python_mystem-0.0.2.dist-info/metadata.json
python_mystem-0.0.2.dist-info/top_level.txt
